drf_nested_browsable/__init__.py
drf_nested_browsable/serializers.py
drf_nested_browsable/templates/writable_list.html
drf_nested_browsable/templatetags/__init__.py
drf_nested_browsable/templatetags/drf_nested_browsable.py
drf_nested_browsable-0.4.1.dist-info/METADATA
drf_nested_browsable-0.4.1.dist-info/WHEEL
drf_nested_browsable-0.4.1.dist-info/RECORD
