Metadata-Version: 2.1
Name: drf-nested-browsable
Version: 0.4.1
Summary: Writable nested serializers with forms for the Browsable API
Home-page: https://pierre-couy.dev/projects/drf-nested-browsable.html
License: MIT
Keywords: django,rest framework,drf,browsable api,nested serializers
Author: Pierre Couy
Author-email: contact@pierre-couy.dev
Requires-Python: >=3.10,<4.0
Classifier: Development Status :: 2 - Pre-Alpha
Classifier: Framework :: Django
Classifier: Intended Audience :: Developers
Classifier: License :: OSI Approved :: MIT License
Classifier: Programming Language :: Python :: 3
Classifier: Programming Language :: Python :: 3.10
Classifier: Programming Language :: Python :: 3.11
Classifier: Programming Language :: Python :: 3.12
Requires-Dist: django (>=4.2,<6.0)
Requires-Dist: djangorestframework (>=3.14.0,<4.0.0)
Requires-Dist: djangorestframework-recursive (>=0.1.2,<0.2.0)
Project-URL: Repository, https://github.com/pcouy/drf-nested-browsable
